<?xml version='1.0' encoding='WINDOWS-1251'?>
<string_table>
    <string id="st_open_adv_ui">
        <text>
            Відкрити розширений інтерфейс
        </text>
    </string>
    <string id="st_freeze">
        <text>
            Заморозити
        </text>
    </string>
    <string id="st_unfreeze">
        <text>
            Розморозити
        </text>
    </string>
    <string id="st_open_connections">
        <text>
            Керування з'єднаннями
        </text>
    </string>
    <string id="st_not_implemented">
        <text>
            Буде реалізовано
        </text>
    </string>
</string_table>
