<?xml version='1.0' encoding='WINDOWS-1251'?>
<string_table>
    <string id="st_mil_car">
        <text>
            Військове автомобільне радіо
        </text>
    </string>
    <string id="st_mil_car_descr">
        <text>
            Військові радіостанції іноді знаходять у розбитих автомобілях. Для більшості -
            мотлох, але, можливо, хтось за нього добре заплатить.
        </text>
    </string>
    <string id="st_mil_amp">
        <text>
            Модуль радіопідсилення
        </text>
    </string>
    <string id="st_mil_amp_descr">
        <text>
            Згорілий військовий підсилювач сигналу, який вирвали з покинутої машини. Мотлох
            для більшості, але може бути цінним для потрібних людей.
        </text>
    </string>
    <string id="ui_mcm_kit_rework_title">
        <text>
            Упс.
        </text>
    </string>
    <string id="ui_mcm_menu_kit_rework">
        <text>
            Переробка світових спавнів
        </text>
    </string>
    <string id="ui_mcm_kit_rework_reset_kits">
        <text>
            Поставте галочку і натисніть "Застосувати" внизу, щоб скинути набори.
        </text>
    </string>
    <string id="ui_mcm_kitspawn_min">
        <text>
            Мінімальний набір інструментів на зону
        </text>
    </string>
    <string id="ui_mcm_kitspawn_max">
        <text>
            Максимальний набір інструментів на зону
        </text>
    </string>
    <string id="ui_mcm_kitspawn_min_desc">
        <text>
            Мінімальний набір інструментів на зону. Сюди входять Базовий, Просунутий та
            Експертний інструменти, а також зброярські інструменти, набори для виготовлення
            ліків, легкі, середні, важкі набори та набори для ремонту шоломів. Не всі набори
            можна знайти в усіх зонах. Наприклад, експертні інструменти не можна знайти в
            найпівденніших зонах.
        </text>
    </string>
    <string id="ui_mcm_kitspawn_max_desc">
        <text>
            Максимальний набір інструментів на зону. Сюди входять Базовий, Просунутий та
            Експертний інструменти, а також зброярські інструменти, набори для виготовлення
            ліків, легкі, середні, важкі набори та набори для ремонту шоломів. Не всі набори
            можна знайти в усіх зонах. Наприклад, експертні інструменти не можна знайти в
            найпівденніших зонах.
        </text>
    </string>
    <string id="ui_mcm_kitspawn_valuables_min">
        <text>
            Мінімум інших цінних речей
        </text>
    </string>
    <string id="ui_mcm_kitspawn_valuables_max">
        <text>
            Максимум інших цінних речей
        </text>
    </string>
    <string id="ui_mcm_kitspawn_valuables_min_desc">
        <text>
            Мінімум інших цінностей, що не належать до інструментарію, таких як набори для
            покращення (раніше їх знаходили лише на трупах), різні набори для чищення, LLMC,
            навіть робоча фара, ехолот або мультитул, якщо вам дійсно пощастило.
        </text>
    </string>
    <string id="ui_mcm_kitspawn_valuables_max_desc">
        <text>
            Максимум інших цінностей, що не належать до інструментарію, таких як набори для
            апгрейду (раніше їх знаходили лише на трупах), різні набори для чищення, LLMC,
            навіть робоча фара, ехолот або мультитул, якщо вам дійсно пощастило.
        </text>
    </string>
</string_table>
